cms_articles/__init__.py
cms_articles/admin/__init__.py
cms_articles/admin/article.py
cms_articles/admin/attribute.py
cms_articles/admin/category.py
cms_articles/admin/forms.py
cms_articles/api.py
cms_articles/apps.py
cms_articles/archive.py
cms_articles/article_rendering.py
cms_articles/cms_apps.py
cms_articles/cms_plugins.py
cms_articles/cms_toolbars.py
cms_articles/conf/__init__.py
cms_articles/conf/default_settings.py
cms_articles/import_wordpress/__init__.py
cms_articles/import_wordpress/admin.py
cms_articles/import_wordpress/apps.py
cms_articles/import_wordpress/forms.py
cms_articles/import_wordpress/management/__init__.py
cms_articles/import_wordpress/management/commands/__init__.py
cms_articles/import_wordpress/management/commands/cms_import_wordpress.py
cms_articles/import_wordpress/migrations/0001_initial.py
cms_articles/import_wordpress/migrations/0002_update.py
cms_articles/import_wordpress/migrations/__init__.py
cms_articles/import_wordpress/models.py
cms_articles/import_wordpress/templates/cms_articles/import_wordpress/cms_import.html
cms_articles/import_wordpress/templates/cms_articles/import_wordpress/form.html
cms_articles/import_wordpress/utils.py
cms_articles/locale/cs/LC_MESSAGES/django.mo
cms_articles/locale/cs/LC_MESSAGES/django.po
cms_articles/migrations/0001_initial.py
cms_articles/migrations/0002_remove_title_excerpt.py
cms_articles/migrations/0003_description_image.py
cms_articles/migrations/0004_categories.py
cms_articles/migrations/0005_attributes.py
cms_articles/migrations/0006_order_date.py
cms_articles/migrations/0007_plugins.py
cms_articles/migrations/0008_cms_3_4.py
cms_articles/migrations/0009_number_min_value.py
cms_articles/migrations/0010_remove_article_revision_id.py
cms_articles/migrations/0011_attribute_site.py
cms_articles/migrations/0012_protect_keys.py
cms_articles/migrations/__init__.py
cms_articles/models/__init__.py
cms_articles/models/article.py
cms_articles/models/attribute.py
cms_articles/models/category.py
django_cms_articles-2.2.0.dist-info/METADATA
django_cms_articles-2.2.0.dist-info/WHEEL
django_cms_articles-2.2.0.dist-info/licenses/LICENSE
django_cms_articles-2.2.0.dist-info/RECORD
