Metadata-Version: 2.4
Name: django-cms-articles
Version: 2.2.0
Summary: django CMS application for managing articles
License: BSD-3-Clause
License-File: LICENSE
Author: Jakub Dorňák
Author-email: jakub.dornak@qbsoftware.cz
Requires-Python: >=3.9,<4.0
Classifier: Development Status :: 5 - Production/Stable
Classifier: Environment :: Web Environment
Classifier: Framework :: Django
Classifier: Framework :: Django :: 2
Classifier: Framework :: Django :: 3
Classifier: Intended Audience :: Developers
Classifier: License :: OSI Approved :: BSD License
Classifier: Natural Language :: Czech
Classifier: Natural Language :: English
Classifier: Operating System :: OS Independent
Classifier: Programming Language :: Python
Classifier: Programming Language :: Python :: 3
Classifier: Programming Language :: Python :: 3.9
Classifier: Programming Language :: Python :: 3.10
Classifier: Programming Language :: Python :: 3.11
Classifier: Programming Language :: Python :: 3.12
Classifier: Programming Language :: Python :: 3.13
Classifier: Programming Language :: Python :: 3.14
Classifier: Topic :: Internet :: WWW/HTTP :: Dynamic Content
Classifier: Topic :: Software Development
Classifier: Topic :: Software Development :: Libraries :: Application Frameworks
Requires-Dist: Django (<4)
Requires-Dist: django-cms (<3.12)
Requires-Dist: django-filer
Requires-Dist: djangocms-text
Requires-Dist: python-dateutil
Project-URL: Repository, https://github.com/qbsoftware/django-cms-articles
